{
    "root_group": {
        "groups": {
            "setup": {
                "groups": {},
                "checks": {
                        "✅ Login status is 200": {
                            "passes": 1,
                            "fails": 0,
                            "name": "✅ Login status is 200",
                            "path": "::setup::✅ Login status is 200",
                            "id": "ef5748235dba7417d2a94f2e9e0282c6"
                        }
                    },
                "name": "setup",
                "path": "::setup",
                "id": "5c0f8025f7e0b6654089e5b00e950f1a"
            }
        },
        "checks": {
            "✅ Create User status is 200": {
                "id": "1afcb8ffb97de0042b15434589c8c74d",
                "passes": 85,
                "fails": 0,
                "name": "✅ Create User status is 200",
                "path": "::✅ Create User status is 200"
            },
            "✅ Response has user object": {
                "fails": 0,
                "name": "✅ Response has user object",
                "path": "::✅ Response has user object",
                "id": "5c7f2b6b8b872d2e9dd3e6261499ac2e",
                "passes": 85
            },
            "✅ User has ID field": {
                "passes": 85,
                "fails": 0,
                "name": "✅ User has ID field",
                "path": "::✅ User has ID field",
                "id": "54f76e3975fa932ae6be3a7e628cf71d"
            },
            "✅ User email matches request": {
                "name": "✅ User email matches request",
                "path": "::✅ User email matches request",
                "id": "5030fb22a471d298a619ba779b77a815",
                "passes": 85,
                "fails": 0
            },
            "✅ User name matches request": {
                "name": "✅ User name matches request",
                "path": "::✅ User name matches request",
                "id": "7b79130807f76f3de350f49012fbda7c",
                "passes": 85,
                "fails": 0
            },
            "✅ User role is set correctly": {
                "name": "✅ User role is set correctly",
                "path": "::✅ User role is set correctly",
                "id": "fe928c112cfb09b313a4cb181c799a1f",
                "passes": 85,
                "fails": 0
            },
            "✅ User ID format is valid": {
                "name": "✅ User ID format is valid",
                "path": "::✅ User ID format is valid",
                "id": "f93475207b262c58d68191669b0ef0b2",
                "passes": 85,
                "fails": 0
            },
            "✅ User email format is valid": {
                "fails": 0,
                "name": "✅ User email format is valid",
                "path": "::✅ User email format is valid",
                "id": "1fc0216ce0f1a6f8a1cbbe85edb620d3",
                "passes": 85
            },
            "✅ User has timestamps": {
                "id": "3ef5f3041872facd78bf2089566d818b",
                "passes": 85,
                "fails": 0,
                "name": "✅ User has timestamps",
                "path": "::✅ User has timestamps"
            },
            "✅ User role is valid": {
                "name": "✅ User role is valid",
                "path": "::✅ User role is valid",
                "id": "dc17da2dd65bad1205f330e8a551fedd",
                "passes": 85,
                "fails": 0
            }
        },
        "name": "",
        "path": "",
        "id": "d41d8cd98f00b204e9800998ecf8427e"
    },
    "metrics": {
        "iterations": {
            "count": 85,
            "rate": 1.6264994215000803
        },
        "vus": {
            "max": 3,
            "value": 1,
            "min": 0
        },
        "http_req_waiting": {
            "min": 440.9549,
            "med": 459.15954999999997,
            "max": 902.1768,
            "p(90)": 491.2903,
            "p(95)": 518.954375,
            "avg": 473.8065418604648
        },
        "http_req_duration{expected_response:true}": {
            "min": 441.3369,
            "med": 459.42134999999996,
            "max": 903.0289,
            "p(90)": 491.47929999999997,
            "p(95)": 519.2455,
            "avg": 474.0966511627904
        },
        "data_received": {
            "count": 67430,
            "rate": 1290.292423432358
        },
        "vus_max": {
            "value": 3,
            "min": 3,
            "max": 3
        },
        "api_failures": {
            "count": 0,
            "rate": 0,
            "thresholds": {
                "count<5": false
            }
        },
        "iteration_duration": {
            "max": 2300.0563,
            "p(90)": 1509.9489600000002,
            "p(95)": 1725.8313599999997,
            "avg": 1502.6607364705874,
            "min": 1442.5746,
            "med": 1462.0379
        },
        "http_req_tls_handshaking": {
            "avg": 24.390491860465115,
            "min": 0,
            "med": 0,
            "max": 546.4884,
            "p(90)": 0,
            "p(95)": 0
        },
        "http_req_connecting": {
            "avg": 11.947513953488373,
            "min": 0,
            "med": 0,
            "max": 264.5743,
            "p(90)": 0,
            "p(95)": 0
        },
        "http_req_receiving": {
            "avg": 0.27793023255813953,
            "min": 0,
            "med": 0.0874,
            "max": 1.364,
            "p(90)": 0.7733,
            "p(95)": 0.8608250000000001
        },
        "http_req_failed": {
            "passes": 0,
            "fails": 86,
            "value": 0
        },
        "data_sent": {
            "count": 46314,
            "rate": 886.2316965571143
        },
        "http_req_blocked": {
            "p(95)": 0.338275,
            "avg": 36.41505813953488,
            "min": 0,
            "med": 0,
            "max": 812.6183,
            "p(90)": 0
        },
        "http_req_duration": {
            "avg": 474.0966511627904,
            "min": 441.3369,
            "med": 459.42134999999996,
            "max": 903.0289,
            "p(90)": 491.47929999999997,
            "p(95)": 519.2455,
            "thresholds": {
                "p(95)<3000": false
            }
        },
        "successful_requests": {
            "fails": 0,
            "passes": 85,
            "thresholds": {
                "rate>0.95": false
            },
            "value": 1
        },
        "http_reqs": {
            "count": 86,
            "rate": 1.6456347088118461
        },
        "http_req_sending": {
            "p(95)": 0,
            "avg": 0.012179069767441862,
            "min": 0,
            "med": 0,
            "max": 0.546,
            "p(90)": 0
        },
        "checks": {
            "passes": 851,
            "fails": 0,
            "thresholds": {
                "rate>0.95": false
            },
            "value": 1
        }
    },
    "setup_data": {
        "token": "54gr8j3LD2Iwvg85DlDVfnpBlCQLMb3v",
        "userId": "mHe2a4J4yxEBTzW2M0lhSliJzoeRclIx",
        "sessionCookie": "__Secure-better-auth.session_token=54gr8j3LD2Iwvg85DlDVfnpBlCQLMb3v.mo7t4XXzuXHDHM1XM6xTtGIXAFKv52fty3ZO1TYa120%3D"
    }
}