{
    "root_group": {
        "checks": {
            "✅ Ban user status is 200": {
                "name": "✅ Ban user status is 200",
                "path": "::✅ Ban user status is 200",
                "id": "352f074713c6bfa643ee478bc019ec37",
                "passes": 33,
                "fails": 0
            },
            "✅ User is marked as banned": {
                "name": "✅ User is marked as banned",
                "path": "::✅ User is marked as banned",
                "id": "28f1a350f46651846a7b5cc863abf721",
                "passes": 33,
                "fails": 0
            },
            "✅ Unban user status is 200": {
                "name": "✅ Unban user status is 200",
                "path": "::✅ Unban user status is 200",
                "id": "76bd75d35b3929612f0db4b88c62a143",
                "passes": 33,
                "fails": 0
            },
            "✅ User is marked as unbanned": {
                "fails": 0,
                "name": "✅ User is marked as unbanned",
                "path": "::✅ User is marked as unbanned",
                "id": "7c4f3001bcd859ade86f953d266b7d59",
                "passes": 33
            }
        },
        "name": "",
        "path": "",
        "id": "d41d8cd98f00b204e9800998ecf8427e",
        "groups": {
            "setup": {
                "path": "::setup",
                "id": "5c0f8025f7e0b6654089e5b00e950f1a",
                "groups": {},
                "checks": {
                        "✅ Login status is 200": {
                            "name": "✅ Login status is 200",
                            "path": "::setup::✅ Login status is 200",
                            "id": "ef5748235dba7417d2a94f2e9e0282c6",
                            "passes": 1,
                            "fails": 0
                        },
                        "✅ List users status is 200": {
                            "name": "✅ List users status is 200",
                            "path": "::setup::✅ List users status is 200",
                            "id": "f9abb2831c9ad981017968fc4b6b12c1",
                            "passes": 1,
                            "fails": 0
                        }
                    },
                "name": "setup"
            }
        }
    },
    "metrics": {
        "http_req_receiving": {
            "avg": 0.5642434117647055,
            "min": 0.039313,
            "med": 0.074113,
            "max": 33.269408,
            "p(90)": 0.0971736,
            "p(95)": 0.11192854999999999
        },
        "ban_failures": {
            "count": 0,
            "rate": 0,
            "thresholds": {
                "count<5": false
            }
        },
        "http_req_sending": {
            "avg": 0.03525938235294118,
            "min": 0.011632,
            "med": 0.0324805,
            "max": 0.095719,
            "p(90)": 0.04661420000000001,
            "p(95)": 0.05653019999999999
        },
        "data_received": {
            "count": 196079,
            "rate": 6166.454866710059
        },
        "unban_successful_requests": {
            "passes": 33,
            "fails": 0,
            "thresholds": {
                "rate>0.95": false
            },
            "value": 1
        },
        "http_req_connecting": {
            "avg": 1.9317091470588235,
            "min": 0,
            "med": 0,
            "max": 37.202456,
            "p(90)": 0,
            "p(95)": 19.724418349999954
        },
        "iterations": {
            "count": 33,
            "rate": 1.0378113444144041
        },
        "http_req_blocked": {
            "min": 0.003216,
            "med": 0.0058505,
            "max": 113.16765,
            "p(90)": 0.0071503,
            "p(95)": 60.01873274999988,
            "avg": 6.088810514705885
        },
        "vus": {
            "value": 1,
            "min": 1,
            "max": 3
        },
        "http_req_duration": {
            "p(90)": 48.666969300000005,
            "p(95)": 57.63400749999999,
            "avg": 46.68218052941176,
            "min": 37.799204,
            "med": 41.0117725,
            "max": 240.605371,
            "thresholds": {
                "p(95)<3000": false
            }
        },
        "http_req_duration{expected_response:true}": {
            "avg": 46.68218052941176,
            "min": 37.799204,
            "med": 41.0117725,
            "max": 240.605371,
            "p(90)": 48.666969300000005,
            "p(95)": 57.63400749999999
        },
        "vus_max": {
            "value": 3,
            "min": 3,
            "max": 3
        },
        "http_reqs": {
            "count": 68,
            "rate": 2.138520346066045
        },
        "checks": {
            "passes": 134,
            "fails": 0,
            "thresholds": {
                "rate>0.95": false
            },
            "value": 1
        },
        "http_req_tls_handshaking": {
            "min": 0,
            "med": 0,
            "max": 75.853505,
            "p(90)": 0,
            "p(95)": 40.16204269999991,
            "avg": 4.050882941176471
        },
        "data_sent": {
            "count": 37081,
            "rate": 1166.1540140069853
        },
        "ban_successful_requests": {
            "passes": 33,
            "fails": 0,
            "thresholds": {
                "rate>0.95": false
            },
            "value": 1
        },
        "unban_failures": {
            "count": 0,
            "rate": 0,
            "thresholds": {
                "count<5": false
            }
        },
        "http_req_failed": {
            "fails": 68,
            "passes": 0,
            "value": 0
        },
        "http_req_waiting": {
            "p(90)": 48.560021000000006,
            "p(95)": 57.53025454999999,
            "avg": 46.08267773529412,
            "min": 37.691472,
            "med": 40.9071475,
            "max": 240.428922
        },
        "iteration_duration": {
            "avg": 2096.7318316363635,
            "min": 2078.504494,
            "med": 2082.960263,
            "max": 2215.462361,
            "p(90)": 2113.000426,
            "p(95)": 2179.4143034
        }
    },
    "setup_data": {
        "sessionCookie": "__Secure-better-auth.session_token=aWcdMTZ7NCgXzSmEDrmJiaO8ZnL2UhdL.UnscPnXcNeJWI5o1IEw%2B0LVA7pmtpDNhS71lsv7trnw%3D",
        "token": "aWcdMTZ7NCgXzSmEDrmJiaO8ZnL2UhdL",
        "users": [
            {
                "name": "Test User 1762271975462_840 - Updated - Updated - Updated - Updated - Updated - Updated - Updated - Updated - Updated - Updated - Updated - Updated - Updated - Updated - Updated - Updated - Updated - Updated - Updated - Updated - Updated - Updated - Updated - Updated - Updated - Updated - Updated - Updated - Updated - Updated - Updated - Updated - Updated - Updated - Updated - Updated - Updated - Updated - Updated - Updated - Updated - Updated - Updated - Updated - Updated - Updated - Updated - Updated - Updated - Updated - Updated - Updated - Updated - Updated - Updated - Updated - Updated - Updated - Updated - Updated - Updated - Updated - Updated - Updated - Updated - Updated - Updated - Updated - Updated - Updated - Updated - Updated - Updated - Updated - Updated - Updated - Updated - Updated - Updated - Updated - Updated - Updated - Updated - Updated - Updated - Updated - Updated - Updated - Updated - Updated - Updated - Updated - Updated - Updated - Updated - Updated - Updated - Updated - Updated - Updated - Updated - Updated - Updated - Updated - Updated - Updated - Updated - Updated - Updated - Updated - Updated - Updated - Updated - Updated - Updated - Updated - Updated - Updated - Updated - Updated - Updated - Updated - Updated - Updated - Updated - Updated - Updated - Updated - Updated - Updated - Updated - Updated - Updated - Updated - Updated - Updated - Updated - Updated - Updated - Updated - Updated - Updated - Updated - Updated - Updated - Updated - Updated - Updated - Updated - Updated - Updated - Updated - Updated - Updated - Updated - Updated - Updated - Updated - Updated - Updated - Updated - Updated - Updated - Updated - Updated - Updated - Updated - Updated - Updated - Updated - Updated - Updated - Updated - Updated - Updated - Updated - Updated - Updated - Updated - Updated - Updated - Updated - Updated - Updated - Updated - Updated - Updated - Updated - Updated - Updated - Updated - Updated - Updated - Updated - Updated - Updated - Updated - Updated - Updated - Updated - Updated - Updated - Updated - Updated - Updated - Updated - Updated - Updated - Updated - Updated - Updated - Updated - Updated - Updated - Updated - Updated - Updated - Updated - Updated - Updated - Updated - Updated - Updated - Updated - Updated - Updated - Updated - Updated - Updated - Updated - Updated - Updated - Updated - Updated - Updated - Updated - Updated - Updated - Updated - Updated - Updated - Updated - Updated - Updated - Updated - Updated - Updated - Updated - Updated - Updated - Updated - Updated - Updated - Updated - Updated - Updated - Updated - Updated - Updated - Updated - Updated - Updated - Updated - Updated - Updated - Updated - Updated - Updated - Updated - Updated - Updated - Updated - Updated - Updated - Updated - Updated - Updated - Updated - Updated - Updated - Updated - Updated - Updated - Updated - Updated - Updated - Updated - Updated - Updated - Updated - Updated - Updated - Updated - Updated - Updated - Updated - Updated - Updated - Updated - Updated - Updated - Updated - Updated - Updated - Updated - Updated - Updated - Updated - Updated - Updated - Updated - Updated - Updated - Updated - Updated - Updated - Updated - Updated - Updated - Updated - Updated - Updated - Updated - Updated - Updated - Updated - Updated - Updated - Updated - Updated - Updated - Updated - Updated - Updated - Updated - Updated - Updated - Updated - Updated - Updated - Updated - Updated - Updated - Updated - Updated - Updated - Updated - Updated - Updated - Updated - Updated - Updated - Updated - Updated - Updated - Updated - Updated - Updated - Updated - Updated - Updated - Updated - Updated - Updated - Updated - Updated - Updated - Updated - Updated - Updated - Updated - Updated - Updated - Updated - Updated - Updated - Updated - Updated - Updated - Updated - Updated - Updated - Updated - Updated - Updated - Updated - Updated - Updated - Updated - Updated - Updated - Updated - Updated - Updated - Updated - Updated - Updated - Updated - Updated - Updated - Updated - Updated - Updated - Updated - Updated - Updated - Updated - Updated - Updated - Updated - Updated - Updated - Updated - Updated - Updated - Updated - Updated - Updated - Updated - Updated - Updated - Updated - Updated - Updated - Updated - Updated - Updated - Updated - Updated - Updated - Updated - Updated - Updated - Updated - Updated - Updated - Updated - Updated - Updated - Updated - Updated - Updated - Updated - Updated - Updated - Updated - Updated - Updated - Updated - Updated - Updated - Updated - Updated - Updated - Updated - Updated - Updated - Updated - Updated - Updated - Updated - Updated - Updated - Updated - Updated - Updated - Updated - Updated - Updated - Updated - Updated - Updated - Updated - Updated - Updated - Updated - Updated - Updated - Updated - Updated - Updated - Updated - Updated - Updated - Updated - Updated - Updated - Updated - Updated - Updated - Updated - Updated - Updated - Updated - Updated - Updated - Updated - Updated - Updated - Updated - Updated - Updated - Updated - Updated - Updated - Updated - Updated - Updated - Updated - Updated - Updated - Updated - Updated - Updated - Updated - Updated - Updated - Updated - Updated - Updated - Updated - Updated - Updated - Updated - Updated - Updated - Updated - Updated - Updated - Updated - Updated - Updated - Updated - Updated - Updated - Updated - Updated - Updated - Updated - Updated - Updated - Updated - Updated - Updated - Updated - Updated - Updated - Updated - Updated - Updated - Updated - Updated - Updated - Updated - Updated - Updated - Updated - Updated - Updated - Updated - Updated - Updated - Updated - Updated - Updated - Updated - Updated - Updated - Updated - Updated - Updated - Updated - Updated - Updated - Updated - Updated - Updated - Updated - Updated - Updated - Updated - Updated - Updated - Updated - Updated - Updated - Updated - Updated - Updated - Updated - Updated - Updated - Updated - Updated - Updated - Updated - Updated - Updated - Updated - Updated - Updated - Updated - Updated - Updated - Updated - Updated - Updated - Updated - Updated - Updated - Updated - Updated - Updated - Updated - Updated - Updated - Updated - Updated - Updated - Updated - Updated - Updated - Updated - Updated - Updated - Updated - Updated - Updated - Updated - Updated - Updated - Updated - Updated - Updated - Updated - Updated - Updated - Updated - Updated - Updated - Updated - Updated - Updated - Updated - Updated - Updated - Updated - Updated - Updated - Updated - Updated - Updated - Updated - Updated - Updated - Updated - Updated - Updated - Updated - Updated - Updated - Updated - Updated - Updated - Updated - Updated - Updated - Updated - Updated - Updated - Updated - Updated - Updated - Updated - Updated - Updated - Updated - Updated - Updated - Updated - Updated - Updated - Updated - Updated - Updated - Updated - Updated - Updated - Updated - Updated - Updated - Updated - Updated - Updated - Updated - Updated - Updated - Updated - Updated - Updated - Updated - Updated - Updated - Updated - Updated - Updated - Updated - Updated - Updated - Updated - Updated - Updated - Updated - Updated - Updated - Updated - Updated - Updated - Updated - Updated - Updated - Updated - Updated - Updated - Updated - Updated - Updated - Updated - Updated - Updated - Updated - Updated - Updated - Updated - Updated - Updated - Updated - Updated - Updated - Updated - Updated - Updated - Updated - Updated - Updated - Updated - Updated - Updated - Updated - Updated - Updated - Updated - Updated - Updated - Updated - Updated - Updated - Updated - Updated - Updated - Updated - Updated - Updated - Updated - Updated - Updated - Updated - Updated - Updated - Updated - Updated - Updated - Updated - Updated - Updated - Updated - Updated - Updated - Updated - Updated - Updated - Updated - Updated - Updated - Updated - Updated - Updated - Updated - Updated - Updated - Updated - Updated - Updated - Updated - Updated - Updated - Updated - Updated - Updated - Updated - Updated - Updated - Updated - Updated - Updated - Updated - Updated - Updated - Updated - Updated - Updated - Updated - Updated - Updated - Updated - Updated - Updated - Updated - Updated - Updated - Updated - Updated - Updated - Updated - Updated - Updated - Updated - Updated - Updated - Updated - Updated - Updated - Updated - Updated - Updated - Updated - Updated - Updated - Updated - Updated - Updated - Updated - Updated - Updated - Updated - Updated - Updated - Updated - Updated - Updated - Updated - Updated - Updated - Updated - Updated - Updated - Updated - Updated - Updated - Updated - Updated - Updated - Updated - Updated - Updated - Updated - Updated - Updated - Updated - Updated - Updated - Updated - Updated - Updated - Updated - Updated - Updated - Updated - Updated - Updated - Updated - Updated - Updated - Updated - Updated - Updated - Updated - Updated - Updated - Updated - Updated - Updated - Updated - Updated - Updated - Updated - Updated - Updated - Updated - Updated - Updated - Updated - Updated - Updated - Updated - Updated - Updated - Updated - Updated - Updated - Updated - Updated - Updated - Updated - Updated - Updated - Updated - Updated - Updated - Updated - Updated - Updated - Updated - Updated - Updated - Updated - Updated - Updated - Updated - Updated - Updated - Updated - Updated - Updated - Updated - Updated - Updated - Updated - Updated - Updated - Updated - Updated - Updated - Updated - Updated - Updated - Updated - Updated - Updated - Updated - Updated - Updated - Updated - Updated - Updated - Updated - Updated - Updated - Updated - Updated - Updated - Updated - Updated - Updated - Updated - Updated - Updated - Updated - Updated - Updated - Updated - Updated - Updated - Updated - Updated - Updated - Updated - Updated - Updated - Updated - Updated - Updated - Updated - Updated - Updated - Updated - Updated - Updated - Updated - Updated - Updated - Updated - Updated - Updated - Updated - Updated - Updated - Updated - Updated - Updated - Updated - Updated - Updated - Updated - Updated - Updated - Updated - Updated - Updated - Updated - Updated - Updated - Updated - Updated - Updated - Updated - Updated - Updated - Updated - Updated - Updated - Updated - Updated - Updated - Updated - Updated - Updated - Updated - Updated - Updated - Updated - Updated - Updated - Updated - Updated - Updated - Updated - Updated - Updated - Updated - Updated - Updated - Updated - Updated - Updated - Updated - Updated - Updated - Updated - Updated - Updated - Updated - Updated - Updated - Updated - Updated - Updated - Updated - Updated - Updated - Updated - Updated - Updated - Updated - Updated - Updated - Updated - Updated - Updated - Updated - Updated - Updated - Updated - Updated - Updated - Updated - Updated - Updated - Updated - Updated - Updated - Updated - Updated - Updated - Updated - Updated - Updated - Updated - Updated - Updated - Updated - Updated - Updated - Updated - Updated - Updated - Updated - Updated - Updated - Updated - Updated - Updated - Updated - Updated - Updated - Updated - Updated - Updated - Updated - Updated - Updated - Updated - Updated - Updated - Updated - Updated - Updated - Updated - Updated - Updated - Updated - Updated - Updated - Updated - Updated - Updated - Updated - Updated - Updated - Updated - Updated - Updated - Updated - Updated - Updated - Updated - Updated - Updated - Updated - Updated - Updated - Updated - Updated - Updated - Updated - Updated - Updated - Updated - Updated - Updated - Updated - Updated - Updated - Updated - Updated - Updated - Updated - Updated - Updated - Updated - Updated - Updated - Updated - Updated - Updated - Updated - Updated - Updated - Updated - Updated - Updated - Updated - Updated - Updated - Updated - Updated - Updated - Updated - Updated - Updated - Updated - Updated - Updated - Updated - Updated - Updated - Updated - Updated - Updated - Updated - Updated - Updated - Updated",
                "role": "scribe",
                "banReason": null,
                "canEdit": false,
                "email": "testuser17622719754622910@example.com",
                "image": null,
                "banned": false,
                "createdAt": "2025-11-04T15:59:40.496Z",
                "templateId": [
                    28
                ],
                "twoFactorEnabled": null,
                "banExpires": null,
                "emailVerified": false,
                "id": "020vkrt3PpfgeofwnyNPGnG7D5VarFGN",
                "lang": [
                    "en"
                ],
                "updatedAt": "2025-11-11T17:28:38.458Z"
            },
            {
                "banned": false,
                "createdAt": "2025-11-05T13:41:01.660Z",
                "twoFactorEnabled": null,
                "canEdit": false,
                "lang": [
                    "en"
                ],
                "name": "Test User 1762350056768_939",
                "email": "testuser17623500567684565@example.com",
                "templateId": [
                    28
                ],
                "updatedAt": "2025-11-05T13:41:01.660Z",
                "banExpires": null,
                "emailVerified": false,
                "id": "0258KERBPx3BXhzjbb1MlXInhpzhZhEK",
                "image": null,
                "role": "scribeAdmin",
                "banReason": null
            },
            {
                "canEdit": false,
                "createdAt": "2025-11-04T14:59:16.721Z",
                "role": "provider",
                "banExpires": null,
                "banReason": null,
                "banned": false,
                "emailVerified": false,
                "id": "02fW6ijcGhcEiT5mS3fHXkARfrk34qBK",
                "lang": [
                    "en"
                ],
                "updatedAt": "2025-11-04T15:50:24.768Z",
                "name": "Test User 1762268356708_756 - Updated - Updated - Updated - Updated - Updated - Updated - Updated - Updated - Updated - Updated - Updated - Updated - Updated - Updated - Updated - Updated - Updated - Updated - Updated - Updated - Updated - Updated - Updated - Updated - Updated - Updated - Updated - Updated - Updated - Updated - Updated - Updated - Updated - Updated - Updated - Updated - Updated - Updated - Updated - Updated - Updated - Updated - Updated - Updated - Updated - Updated - Updated - Updated - Updated - Updated - Updated - Updated - Updated - Updated - Updated - Updated - Updated - Updated - Updated - Updated - Updated - Updated - Updated - Updated - Updated - Updated - Updated - Updated - Updated - Updated - Updated - Updated - Updated - Updated - Updated - Updated - Updated - Updated - Updated - Updated - Updated - Updated - Updated - Updated - Updated - Updated",
                "twoFactorEnabled": null,
                "templateId": [
                    28
                ],
                "email": "testuser17622683567082085@example.com",
                "image": null
            },
            {
                "banExpires": null,
                "lang": [
                    "en"
                ],
                "role": "demo",
                "twoFactorEnabled": null,
                "banReason": null,
                "createdAt": "2025-11-11T17:14:17.512Z",
                "image": null,
                "templateId": [
                    28
                ],
                "updatedAt": "2025-11-11T17:14:17.512Z",
                "canEdit": false,
                "name": "Test User 1762881251594_20",
                "banned": false,
                "email": "testuser17628812515948573@example.com",
                "emailVerified": false,
                "id": "02kYSyMTcNCq7YvXOByVyiI2ZQgcgwzX"
            },
            {
                "updatedAt": "2025-11-04T14:59:15.804Z",
                "createdAt": "2025-10-31T16:13:11.773Z",
                "role": "scribe",
                "banReason": null,
                "canEdit": false,
                "email": "testuser17619271874333529@example.com",
                "emailVerified": false,
                "lang": [
                    "en"
                ],
                "banExpires": null,
                "banned": false,
                "image": null,
                "twoFactorEnabled": null,
                "id": "030CIaYcl4ICsdrw7raT1WAdm9PicrI7",
                "name": "Test User 1761927187433_573 - Updated - Updated - Updated - Updated - Updated - Updated - Updated - Updated - Updated - Updated - Updated - Updated - Updated - Updated - Updated - Updated - Updated - Updated - Updated - Updated - Updated - Updated - Updated - Updated - Updated - Updated - Updated - Updated - Updated - Updated - Updated - Updated - Updated - Updated - Updated - Updated - Updated - Updated - Updated - Updated - Updated - Updated - Updated - Updated - Updated - Updated - Updated - Updated - Updated - Updated - Updated - Updated - Updated - Updated - Updated - Updated - Updated - Updated - Updated - Updated - Updated - Updated - Updated - Updated - Updated - Updated - Updated - Updated - Updated - Updated - Updated - Updated - Updated - Updated - Updated - Updated - Updated - Updated - Updated - Updated - Updated - Updated - Updated - Updated - Updated - Updated - Updated - Updated - Updated - Updated - Updated - Updated - Updated - Updated - Updated - Updated - Updated - Updated - Updated - Updated - Updated - Updated - Updated - Updated - Updated - Updated - Updated - Updated - Updated - Updated - Updated - Updated - Updated - Updated - Updated - Updated - Updated - Updated - Updated - Updated - Updated - Updated - Updated - Updated - Updated - Updated - Updated - Updated - Updated - Updated - Updated - Updated - Updated - Updated - Updated - Updated - Updated - Updated - Updated - Updated - Updated - Updated - Updated - Updated - Updated - Updated - Updated - Updated - Updated - Updated - Updated - Updated - Updated - Updated - Updated - Updated - Updated - Updated - Updated - Updated - Updated - Updated - Updated - Updated - Updated - Updated - Updated - Updated - Updated - Updated - Updated - Updated - Updated - Updated - Updated - Updated",
                "templateId": [
                    28
                ]
            },
            {
                "image": null,
                "lang": [
                    "en"
                ],
                "templateId": [
                    28
                ],
                "banned": false,
                "banReason": null,
                "canEdit": false,
                "createdAt": "2025-11-03T17:09:49.876Z",
                "emailVerified": false,
                "name": "Test User 1762189785206_790",
                "role": "scribeAdmin",
                "banExpires": null,
                "id": "03JckKJApEfJ9HYQJI9OpDNL8YaCjkAw",
                "twoFactorEnabled": null,
                "updatedAt": "2025-11-03T17:09:49.876Z",
                "email": "testuser17621897852063199@example.com"
            },
            {
                "templateId": [
                    28
                ],
                "email": "testuser17619187508971360@example.com",
                "id": "03wp3h9VWKfEUkmWwOYrd56PglcOEOmo",
                "image": null,
                "name": "Test User 1761918750897_684",
                "updatedAt": "2025-10-31T13:52:35.113Z",
                "banExpires": null,
                "banReason": null,
                "canEdit": false,
                "createdAt": "2025-10-31T13:52:35.113Z",
                "lang": [
                    "en"
                ],
                "role": "provider",
                "twoFactorEnabled": null,
                "banned": false,
                "emailVerified": false
            },
            {
                "canEdit": false,
                "emailVerified": false,
                "lang": [
                    "en"
                ],
                "templateId": [
                    28
                ],
                "updatedAt": "2025-10-31T16:28:38.652Z",
                "banned": false,
                "id": "069Jazl3kTUxtaAuEYKM0VkO1mfW8nJ7",
                "image": null,
                "role": "demo",
                "createdAt": "2025-10-31T16:28:38.652Z",
                "name": "Test User 1761928114296_844",
                "banExpires": null,
                "banReason": null,
                "email": "testuser17619281142962102@example.com",
                "twoFactorEnabled": null
            },
            {
                "id": "06E17QSbfg1kTNbSCKmW7fqTV0oCOMBA",
                "image": null,
                "updatedAt": "2025-11-04T16:21:00.014Z",
                "banReason": null,
                "email": "testuser17622732597899445@example.com",
                "lang": [
                    "en"
                ],
                "name": "Test User 1762273259789_766",
                "twoFactorEnabled": null,
                "banExpires": null,
                "role": "scribe",
                "templateId": [
                    28
                ],
                "emailVerified": false,
                "banned": false,
                "canEdit": false,
                "createdAt": "2025-11-04T16:21:00.014Z"
            },
            {
                "email": "testuser17619271772504834@example.com",
                "emailVerified": false,
                "lang": [
                    "en"
                ],
                "canEdit": false,
                "image": null,
                "role": "scribeAdmin",
                "twoFactorEnabled": null,
                "banExpires": null,
                "createdAt": "2025-10-31T16:13:01.590Z",
                "id": "06fvlwRqAgHINtKACutY9v6NQnEcGs7L",
                "updatedAt": "2025-10-31T16:13:01.590Z",
                "name": "Test User 1761927177250_832",
                "templateId": [
                    28
                ],
                "banReason": null,
                "banned": false
            },
            {
                "banReason": null,
                "banned": false,
                "canEdit": false,
                "emailVerified": false,
                "lang": [
                    "en"
                ],
                "updatedAt": "2025-11-03T14:40:35.035Z",
                "createdAt": "2025-11-03T14:40:35.035Z",
                "email": "testuser17621808305136394@example.com",
                "name": "Test User 1762180830513_735",
                "templateId": [
                    28
                ],
                "twoFactorEnabled": null,
                "banExpires": null,
                "id": "089j8nOqeAMwIqFlnORPYVscoH7hgg3F",
                "image": null,
                "role": "provider"
            },
            {
                "email": "testuser17622719634077561@example.com",
                "image": null,
                "role": "demo",
                "createdAt": "2025-11-04T15:59:28.461Z",
                "name": "Test User 1762271963407_432",
                "twoFactorEnabled": null,
                "banned": false,
                "id": "08FbQVG5aVb2BXeVhflkaHdtZn5Ts0I7",
                "updatedAt": "2025-11-04T15:59:28.461Z",
                "banExpires": null,
                "canEdit": false,
                "emailVerified": false,
                "lang": [
                    "en"
                ],
                "templateId": [
                    28
                ],
                "banReason": null
            },
            {
                "twoFactorEnabled": null,
                "banExpires": null,
                "canEdit": false,
                "createdAt": "2025-11-04T14:49:11.764Z",
                "id": "08XEHE9oNVymuKZ3fHnelwJcHv6UVf4o",
                "name": "Test User 1762267746805_999",
                "updatedAt": "2025-11-04T14:49:11.764Z",
                "templateId": [
                    28
                ],
                "banReason": null,
                "emailVerified": false,
                "image": null,
                "banned": false,
                "email": "testuser17622677468051636@example.com",
                "lang": [
                    "en"
                ],
                "role": "scribe"
            },
            {
                "canEdit": false,
                "email": "testuser17624466143192420@example.com",
                "role": "scribeAdmin",
                "templateId": [
                    28
                ],
                "twoFactorEnabled": null,
                "banReason": null,
                "emailVerified": false,
                "id": "0a1lgGnRg68VRGoM8MAEW0AubG92QTmP",
                "lang": [
                    "en"
                ],
                "updatedAt": "2025-11-06T16:30:19.142Z",
                "banExpires": null,
                "banned": false,
                "createdAt": "2025-11-06T16:30:19.142Z",
                "image": null,
                "name": "Test User 1762446614319_311"
            },
            {
                "banExpires": null,
                "canEdit": false,
                "createdAt": "2025-11-05T14:56:53.335Z",
                "email": "testuser17623546133098743@example.com",
                "twoFactorEnabled": null,
                "updatedAt": "2025-11-05T14:56:53.335Z",
                "banned": false,
                "id": "0apcWPReBVfHjNqKoOQkOgNlcZBuXzOt",
                "image": null,
                "lang": [
                    "en"
                ],
                "templateId": [
                    28
                ],
                "banReason": null,
                "name": "Test User 1762354613309_640",
                "emailVerified": false,
                "role": "provider"
            },
            {
                "banExpires": null,
                "email": "testuser17622719956335502@example.com",
                "id": "0aSIIQPv1MuFSiIRXniNd9rJeBLlcVUs",
                "lang": [
                    "en"
                ],
                "name": "Test User 1762271995633_150",
                "emailVerified": false,
                "twoFactorEnabled": null,
                "canEdit": false,
                "image": null,
                "role": "demo",
                "banReason": null,
                "banned": false,
                "createdAt": "2025-11-04T16:00:00.668Z",
                "templateId": [
                    28
                ],
                "updatedAt": "2025-11-04T16:00:00.668Z"
            },
            {
                "banReason": null,
                "email": "testuser17621901010059490@example.com",
                "canEdit": false,
                "id": "0aV6O7hieKofqQmnNH9cdSQJAtywuxxy",
                "lang": [
                    "en"
                ],
                "role": "scribe",
                "templateId": [
                    28
                ],
                "createdAt": "2025-11-03T17:15:05.662Z",
                "emailVerified": false,
                "name": "Test User 1762190101005_878",
                "updatedAt": "2025-11-03T17:15:05.662Z",
                "twoFactorEnabled": null,
                "banExpires": null,
                "banned": false,
                "image": null
            },
            {
                "canEdit": false,
                "email": "testuser1761583086493@gmail.com",
                "id": "0b9YiMhflZ4Aj6h8gItpfpWOgxW0yoxk",
                "name": "Test User 1761583086493",
                "role": "scribeAdmin",
                "templateId": [
                    28
                ],
                "updatedAt": "2025-10-27T16:38:12.826Z",
                "banned": false,
                "createdAt": "2025-10-27T16:38:12.826Z",
                "emailVerified": false,
                "image": null,
                "lang": [
                    "en"
                ],
                "banExpires": null,
                "banReason": null,
                "twoFactorEnabled": null
            },
            {
                "twoFactorEnabled": null,
                "banned": false,
                "email": "testuser17622677456473926@example.com",
                "id": "0c6eJj2WJkVI3TGufBby001Bw40cg4cP",
                "name": "Test User 1762267745647_462",
                "role": "provider",
                "banExpires": null,
                "canEdit": false,
                "emailVerified": false,
                "lang": [
                    "en"
                ],
                "updatedAt": "2025-11-04T14:49:10.605Z",
                "createdAt": "2025-11-04T14:49:10.605Z",
                "image": null,
                "templateId": [
                    28
                ],
                "banReason": null
            },
            {
                "banReason": null,
                "canEdit": false,
                "name": "Test User 1762176185975_936",
                "twoFactorEnabled": null,
                "createdAt": "2025-11-03T13:23:10.426Z",
                "emailVerified": false,
                "role": "demo",
                "updatedAt": "2025-11-03T13:23:10.426Z",
                "banExpires": null,
                "banned": false,
                "id": "0cAtehTtHHcejNj1t4Edeu3b3wyX2efJ",
                "image": null,
                "lang": [
                    "en"
                ],
                "email": "testuser17621761859754290@example.com",
                "templateId": [
                    28
                ]
            },
            {
                "banReason": null,
                "email": "testuser17621787443244641@example.com",
                "image": null,
                "templateId": [
                    28
                ],
                "banExpires": null,
                "banned": false,
                "lang": [
                    "en"
                ],
                "name": "Test User 1762178744324_165",
                "role": "scribe",
                "canEdit": false,
                "emailVerified": false,
                "twoFactorEnabled": null,
                "updatedAt": "2025-11-03T14:05:48.817Z",
                "createdAt": "2025-11-03T14:05:48.817Z",
                "id": "0CcsbAFoXDuNHcHCjSInNTbdt4lhHPOa"
            },
            {
                "banExpires": null,
                "banReason": null,
                "canEdit": false,
                "image": null,
                "lang": [
                    "en"
                ],
                "role": "scribeAdmin",
                "twoFactorEnabled": null,
                "banned": false,
                "id": "0CeVLs7BzznRYi8q4LuHOE4U0ZVZrB1O",
                "updatedAt": "2025-10-31T15:34:44.160Z",
                "createdAt": "2025-10-31T15:34:44.160Z",
                "email": "testuser17619248841342051@example.com",
                "name": "Test User 1761924884134_726",
                "templateId": [
                    28
                ],
                "emailVerified": false
            },
            {
                "banExpires": null,
                "banned": false,
                "canEdit": false,
                "templateId": [
                    28
                ],
                "createdAt": "2025-10-31T13:52:29.037Z",
                "email": "testuser17619187448209800@example.com",
                "updatedAt": "2025-10-31T13:52:29.037Z",
                "banReason": null,
                "emailVerified": false,
                "image": null,
                "lang": [
                    "en"
                ],
                "name": "Test User 1761918744820_718",
                "role": "provider",
                "id": "0DzspgYwNfQTAMlhrhN8x640jBbihmqx",
                "twoFactorEnabled": null
            },
            {
                "twoFactorEnabled": null,
                "updatedAt": "2025-10-31T15:34:32.008Z",
                "createdAt": "2025-10-31T15:34:32.008Z",
                "email": "testuser17619248719794565@example.com",
                "emailVerified": false,
                "templateId": [
                    28
                ],
                "banExpires": null,
                "banReason": null,
                "canEdit": false,
                "id": "0Er5VjXHCJExD9OJMMuMyYWHLyBGd7N3",
                "lang": [
                    "en"
                ],
                "name": "Test User 1761924871979_584",
                "banned": false,
                "image": null,
                "role": "demo"
            },
            {
                "canEdit": false,
                "email": "testuser17623551312142167@example.com",
                "emailVerified": false,
                "image": null,
                "banExpires": null,
                "createdAt": "2025-11-05T15:05:31.240Z",
                "id": "0f4tIv5AdWwAKgllGqZT60bOnFNHs319",
                "templateId": [
                    28
                ],
                "lang": [
                    "en"
                ],
                "role": "scribe",
                "twoFactorEnabled": null,
                "banReason": null,
                "name": "Test User 1762355131214_316",
                "updatedAt": "2025-11-05T15:05:31.240Z",
                "banned": false
            },
            {
                "canEdit": false,
                "image": null,
                "templateId": [
                    28
                ],
                "email": "testuser17619248818734743@example.com",
                "id": "0FuvmHISgFuvhmx8GHia54C3Vy20Smht",
                "name": "Test User 1761924881873_25",
                "role": "scribeAdmin",
                "updatedAt": "2025-10-31T15:34:41.902Z",
                "banned": false,
                "emailVerified": false,
                "twoFactorEnabled": null,
                "banExpires": null,
                "createdAt": "2025-10-31T15:34:41.902Z",
                "lang": [
                    "en"
                ],
                "banReason": null
            },
            {
                "createdAt": "2025-11-05T15:16:34.715Z",
                "email": "testuser17623557946968041@example.com",
                "emailVerified": false,
                "id": "0gwkEDEUVOpqS9d0fhxpbjdecCLThw1R",
                "twoFactorEnabled": null,
                "banReason": null,
                "canEdit": false,
                "image": null,
                "name": "Test User 1762355794696_854",
                "role": "provider",
                "updatedAt": "2025-11-05T15:16:34.715Z",
                "templateId": [
                    28
                ],
                "banExpires": null,
                "banned": false,
                "lang": [
                    "en"
                ]
            },
            {
                "banExpires": null,
                "email": "testuser17625380133843688@example.com",
                "updatedAt": "2025-11-07T17:53:33.395Z",
                "twoFactorEnabled": null,
                "banned": null,
                "id": "0Hfsw1MonaaQSQzq2BM847bPPLp9HE9D",
                "templateId": [
                    28
                ],
                "banReason": null,
                "canEdit": false,
                "image": null,
                "createdAt": "2025-11-07T17:53:33.395Z",
                "emailVerified": false,
                "lang": [
                    "en"
                ],
                "name": "Test User 1762538013384_450",
                "role": "demo"
            },
            {
                "banReason": null,
                "banned": false,
                "role": "scribe",
                "updatedAt": "2025-10-31T15:24:43.033Z",
                "banExpires": null,
                "id": "0hho8avkd69DbIu4ADJxXyZraUP0Tzj6",
                "name": "Test User 1761924278736_699",
                "templateId": [
                    28
                ],
                "twoFactorEnabled": null,
                "email": "testuser17619242787366206@example.com",
                "emailVerified": false,
                "image": null,
                "canEdit": false,
                "createdAt": "2025-10-31T15:24:43.033Z",
                "lang": [
                    "en"
                ]
            },
            {
                "banExpires": null,
                "image": null,
                "lang": [
                    "en"
                ],
                "name": "Test User 1762538007407_308",
                "updatedAt": "2025-11-07T17:53:27.420Z",
                "canEdit": false,
                "createdAt": "2025-11-07T17:53:27.420Z",
                "email": "testuser17625380074074562@example.com",
                "banned": null,
                "id": "0hytSNkigzjEAsaHYwZJbjfYpm5ICcAE",
                "twoFactorEnabled": null,
                "banReason": null,
                "emailVerified": false,
                "role": "scribe",
                "templateId": [
                    28
                ]
            },
            {
                "twoFactorEnabled": null,
                "banExpires": null,
                "canEdit": false,
                "email": "testuser17623594790287096@example.com",
                "emailVerified": false,
                "banned": null,
                "role": "scribeAdmin",
                "templateId": [
                    28
                ],
                "id": "0IIyXLrxUKnwdb9CS0ewxmcj4xqkSXt7",
                "lang": [
                    "en"
                ],
                "updatedAt": "2025-11-05T16:18:04.080Z",
                "banReason": null,
                "createdAt": "2025-11-05T16:18:04.080Z",
                "image": null,
                "name": "Test User 1762359479028_397"
            },
            {
                "name": "Test User 1762184013340_73",
                "role": "scribe",
                "templateId": [
                    28
                ],
                "createdAt": "2025-11-03T15:33:37.898Z",
                "emailVerified": false,
                "banExpires": null,
                "banReason": null,
                "email": "testuser17621840133407783@example.com",
                "image": null,
                "lang": [
                    "en"
                ],
                "updatedAt": "2025-11-03T15:33:37.898Z",
                "canEdit": false,
                "twoFactorEnabled": null,
                "banned": false,
                "id": "0IMcSOLtqhpRCOJ3mM3cQ6RgjpQ8lkHs"
            },
            {
                "createdAt": "2025-11-03T16:38:27.256Z",
                "lang": [
                    "en"
                ],
                "name": "Test User 1762187907232_106",
                "banned": false,
                "id": "0IS93gsagpVuHzodZNbZUYPDUxyabi1K",
                "templateId": [
                    28
                ],
                "updatedAt": "2025-11-03T16:38:27.256Z",
                "banExpires": null,
                "emailVerified": false,
                "canEdit": false,
                "email": "testuser17621879072324958@example.com",
                "image": null,
                "role": "scribeAdmin",
                "twoFactorEnabled": null,
                "banReason": null
            },
            {
                "canEdit": false,
                "image": null,
                "twoFactorEnabled": null,
                "updatedAt": "2025-10-31T16:28:44.505Z",
                "id": "0iZkCRsqxDpPfFaVdwSot2hgtsimVOt1",
                "role": "scribeAdmin",
                "templateId": [
                    28
                ],
                "banned": false,
                "email": "testuser17619281201507427@example.com",
                "emailVerified": false,
                "name": "Test User 1761928120150_929",
                "banExpires": null,
                "banReason": null,
                "createdAt": "2025-10-31T16:28:44.505Z",
                "lang": [
                    "en"
                ]
            },
            {
                "banExpires": null,
                "banned": false,
                "name": "Test User 1761929343047_345",
                "templateId": [
                    28
                ],
                "updatedAt": "2025-10-31T16:49:07.421Z",
                "id": "0jBboBZa80B1tRgAEQxvOTPenegAnSwU",
                "role": "provider",
                "banReason": null,
                "emailVerified": false,
                "image": null,
                "twoFactorEnabled": null,
                "canEdit": false,
                "createdAt": "2025-10-31T16:49:07.421Z",
                "email": "testuser17619293430474387@example.com",
                "lang": [
                    "en"
                ]
            },
            {
                "banned": null,
                "image": null,
                "templateId": [
                    28
                ],
                "banReason": null,
                "createdAt": "2025-11-07T17:44:52.804Z",
                "emailVerified": false,
                "id": "0Jo0rfqT6dUUQUwlVtB2DPJrYG6F1svj",
                "lang": [
                    "en"
                ],
                "banExpires": null,
                "canEdit": false,
                "email": "testuser+1762537490499@gmail.com",
                "twoFactorEnabled": null,
                "updatedAt": "2025-11-07T17:44:52.804Z",
                "name": "Test User",
                "role": "admin"
            },
            {
                "id": "0k3AFDcHTikEJJbdrPrNDHcWYJYj8cQg",
                "role": "demo",
                "canEdit": false,
                "emailVerified": false,
                "lang": [
                    "en"
                ],
                "banExpires": null,
                "image": null,
                "templateId": [
                    28
                ],
                "banReason": null,
                "banned": false,
                "createdAt": "2025-11-03T17:09:34.927Z",
                "name": "Test User 1762189770275_339",
                "twoFactorEnabled": null,
                "updatedAt": "2025-11-03T17:09:34.927Z",
                "email": "testuser17621897702754988@example.com"
            },
            {
                "twoFactorEnabled": null,
                "banReason": null,
                "createdAt": "2025-11-04T16:21:23.554Z",
                "name": "Test User 1762273283522_379",
                "role": "scribe",
                "canEdit": false,
                "emailVerified": false,
                "image": null,
                "banned": null,
                "id": "0K6ROyruSLUJSEZb0wDYDUcF7x6qhmvB",
                "lang": [
                    "en"
                ],
                "templateId": [
                    28
                ],
                "updatedAt": "2025-11-04T16:21:23.554Z",
                "banExpires": null,
                "email": "testuser17622732835227359@example.com"
            },
            {
                "id": "0Kj1sISorBPB1xxhKhcCi9MfS2SoQfLg",
                "twoFactorEnabled": null,
                "image": null,
                "updatedAt": "2025-10-31T15:37:32.721Z",
                "banReason": null,
                "canEdit": false,
                "createdAt": "2025-10-31T15:37:32.721Z",
                "emailVerified": false,
                "name": "Test User 1761925052700_805",
                "banExpires": null,
                "banned": false,
                "email": "testuser1761925052700566@example.com",
                "lang": [
                    "en"
                ],
                "role": "scribeAdmin",
                "templateId": [
                    28
                ]
            },
            {
                "twoFactorEnabled": null,
                "email": "testuser17620486430048832@example.com",
                "emailVerified": false,
                "id": "0LizQ9SpAr4uBeZfCVRVrvw40vDatOkm",
                "image": null,
                "createdAt": "2025-11-02T01:57:23.016Z",
                "updatedAt": "2025-11-02T01:57:23.016Z",
                "templateId": [
                    28
                ],
                "banReason": null,
                "banned": false,
                "lang": [
                    "en"
                ],
                "role": "provider",
                "banExpires": null,
                "canEdit": false,
                "name": "Test User 1762048643004_262"
            },
            {
                "role": "admin",
                "updatedAt": "2025-11-11T16:18:00.125Z",
                "banExpires": null,
                "image": null,
                "lang": [
                    "en"
                ],
                "name": "Test User 1762877874272_935",
                "twoFactorEnabled": null,
                "email": "testuser17628778742721163@example.com",
                "id": "0mX4GOey7fEhuDyWuMH2kASopjlAt4q5",
                "templateId": [
                    28
                ],
                "banReason": null,
                "canEdit": false,
                "createdAt": "2025-11-11T16:18:00.125Z",
                "banned": null,
                "emailVerified": false
            },
            {
                "templateId": [
                    28
                ],
                "banReason": null,
                "createdAt": "2025-11-03T13:23:00.214Z",
                "updatedAt": "2025-11-03T13:23:00.214Z",
                "canEdit": false,
                "emailVerified": false,
                "image": null,
                "role": "demo",
                "twoFactorEnabled": null,
                "banExpires": null,
                "banned": false,
                "email": "testuser17621761757628700@example.com",
                "id": "0NaVAWVbzpf5RWLb5mMKtexHI0D2U5L4",
                "lang": [
                    "en"
                ],
                "name": "Test User 1762176175762_585"
            },
            {
                "createdAt": "2025-11-04T15:59:37.638Z",
                "updatedAt": "2025-11-04T15:59:37.638Z",
                "canEdit": false,
                "name": "Test User 1762271972604_634",
                "twoFactorEnabled": null,
                "banExpires": null,
                "banReason": null,
                "email": "testuser17622719726045329@example.com",
                "emailVerified": false,
                "id": "0NmZPUDAuvzhvPjlE6SYTvzrYALgU1YA",
                "role": "scribe",
                "banned": null,
                "image": null,
                "lang": [
                    "en"
                ],
                "templateId": [
                    28
                ]
            },
            {
                "emailVerified": false,
                "twoFactorEnabled": null,
                "templateId": [
                    28
                ],
                "banExpires": null,
                "banReason": null,
                "id": "0nnbWYvUbfSmxwCfg4NTFL4Z3v27XMg5",
                "image": null,
                "name": "Test User 1761927203060_666",
                "role": "scribeAdmin",
                "createdAt": "2025-10-31T16:13:27.401Z",
                "email": "testuser1761927203060844@example.com",
                "lang": [
                    "en"
                ],
                "banned": false,
                "canEdit": false,
                "updatedAt": "2025-10-31T16:13:27.401Z"
            },
            {
                "name": "Test User 1761929348833_322",
                "templateId": [
                    28
                ],
                "updatedAt": "2025-10-31T16:49:13.208Z",
                "banExpires": null,
                "emailVerified": false,
                "twoFactorEnabled": null,
                "banReason": null,
                "banned": false,
                "canEdit": false,
                "createdAt": "2025-10-31T16:49:13.208Z",
                "email": "testuser17619293488339678@example.com",
                "id": "0Nv9INYkkWU63mo9yxiJZ9heJPnQDXlk",
                "lang": [
                    "en"
                ],
                "role": "provider",
                "image": null
            },
            {
                "lang": [
                    "en"
                ],
                "twoFactorEnabled": null,
                "banExpires": null,
                "updatedAt": "2025-10-31T14:27:22.393Z",
                "banned": false,
                "emailVerified": false,
                "id": "0oc4VHl5Elb3gaGWo0prxrPyFIFEVdPU",
                "image": null,
                "name": "Test User 1761920838145_283",
                "banReason": null,
                "canEdit": false,
                "email": "testuser17619208381456339@example.com",
                "role": "demo",
                "templateId": [
                    28
                ],
                "createdAt": "2025-10-31T14:27:22.393Z"
            },
            {
                "id": "0oMSeggQcKAkdl0RHxLthPR3tGzhJGNJ",
                "image": null,
                "banExpires": null,
                "role": "scribe",
                "twoFactorEnabled": null,
                "updatedAt": "2025-11-04T16:07:53.253Z",
                "banReason": null,
                "banned": null,
                "createdAt": "2025-11-04T16:07:53.253Z",
                "templateId": [
                    28
                ],
                "email": "testuser17622724681968666@example.com",
                "emailVerified": false,
                "lang": [
                    "en"
                ],
                "name": "Test User 1762272468196_794",
                "canEdit": false
            },
            {
                "createdAt": "2025-11-04T14:58:36.617Z",
                "lang": [
                    "en"
                ],
                "role": "scribeAdmin",
                "banReason": null,
                "emailVerified": false,
                "id": "0OoOnRewcbe9RT5UfhsIGYYTV7Vplb9o",
                "twoFactorEnabled": null,
                "banExpires": null,
                "canEdit": false,
                "email": "testuser17622683164151155@example.com",
                "image": null,
                "templateId": [
                    28
                ],
                "updatedAt": "2025-11-04T14:58:36.617Z",
                "banned": null,
                "name": "Test User 1762268316415_920"
            },
            {
                "banReason": null,
                "canEdit": false,
                "email": "testuser17622732797794991@example.com",
                "id": "0peuz4MFta6GaeGT1zMOTheZ2LfeoJam",
                "createdAt": "2025-11-04T16:21:19.810Z",
                "emailVerified": false,
                "name": "Test User 1762273279779_288",
                "role": "provider",
                "twoFactorEnabled": null,
                "updatedAt": "2025-11-04T16:21:19.810Z",
                "banExpires": null,
                "image": null,
                "templateId": [
                    28
                ],
                "banned": null,
                "lang": [
                    "en"
                ]
            },
            {
                "emailVerified": false,
                "canEdit": false,
                "image": null,
                "templateId": [
                    28
                ],
                "twoFactorEnabled": null,
                "updatedAt": "2025-11-03T14:41:02.704Z",
                "banReason": null,
                "lang": [
                    "en"
                ],
                "name": "Test User 1762180858167_532",
                "banExpires": null,
                "banned": false,
                "id": "0pj8APekhdFAnr9yUDxg3Kb3Iaa9lVJH",
                "role": "demo",
                "createdAt": "2025-11-03T14:41:02.704Z",
                "email": "testuser17621808581676745@example.com"
            },
            {
                "image": null,
                "templateId": [
                    28
                ],
                "twoFactorEnabled": null,
                "id": "0S39qpOqqrWOvMbwlFek5XxrcSAH7hed",
                "role": "admin",
                "banReason": null,
                "createdAt": "2025-11-11T16:18:06.547Z",
                "banExpires": null,
                "canEdit": false,
                "lang": [
                    "en"
                ],
                "name": "Test User 1762877880694_275",
                "updatedAt": "2025-11-11T16:18:06.547Z",
                "banned": null,
                "email": "testuser17628778806946624@example.com",
                "emailVerified": false
            },
            {
                "templateId": [
                    28
                ],
                "canEdit": false,
                "createdAt": "2025-11-04T15:46:17.227Z",
                "email": "testuser17622711722071178@example.com",
                "name": "Test User 1762271172207_74",
                "role": "scribe",
                "twoFactorEnabled": null,
                "banExpires": null,
                "banReason": null,
                "banned": null,
                "emailVerified": false,
                "id": "0SaBNftO1PXyoHL59C6bJpZqeBegNjnY",
                "image": null,
                "lang": [
                    "en"
                ],
                "updatedAt": "2025-11-04T15:46:17.227Z"
            },
            {
                "canEdit": false,
                "id": "0sPRHx83pAh3sA5dbjeUmHMva00xMsy9",
                "role": "admin",
                "templateId": [
                    28
                ],
                "banExpires": null,
                "banReason": null,
                "banned": null,
                "emailVerified": false,
                "image": null,
                "updatedAt": "2025-11-05T15:05:18.841Z",
                "createdAt": "2025-11-05T15:05:18.841Z",
                "name": "Test User 1762355118816_742",
                "twoFactorEnabled": null,
                "email": "testuser17623551188162634@example.com",
                "lang": [
                    "en"
                ]
            },
            {
                "updatedAt": "2025-10-31T15:34:23.193Z",
                "emailVerified": false,
                "image": null,
                "canEdit": false,
                "createdAt": "2025-10-31T15:34:23.193Z",
                "name": "Test User 1761924863166_411",
                "role": "scribeAdmin",
                "banExpires": null,
                "banReason": null,
                "email": "testuser17619248631661413@example.com",
                "id": "0u5wRvfpWEE0FKS39qp3jahCtgTHh6hv",
                "lang": [
                    "en"
                ],
                "templateId": [
                    28
                ],
                "banned": false,
                "twoFactorEnabled": null
            },
            {
                "twoFactorEnabled": null,
                "banExpires": null,
                "createdAt": "2025-11-09T17:53:29.150Z",
                "id": "0Uad6fYg4xpZSGXtG2LodYH96poDOrfT",
                "templateId": [
                    28
                ],
                "emailVerified": false,
                "image": null,
                "name": "Test User 1762710809143_970",
                "banned": null,
                "lang": [
                    "en"
                ],
                "updatedAt": "2025-11-09T17:53:29.150Z",
                "banReason": null,
                "canEdit": false,
                "email": "testuser17627108091431014@example.com",
                "role": "admin"
            },
            {
                "name": "Test User 1762266580819_221",
                "banExpires": null,
                "twoFactorEnabled": null,
                "banReason": null,
                "banned": null,
                "canEdit": false,
                "email": "testuser17622665808196774@example.com",
                "createdAt": "2025-11-04T14:29:45.755Z",
                "id": "0udPAFPJ37zzYkL5Ddki06hAOTFz3f7T",
                "role": "provider",
                "templateId": [
                    28
                ],
                "updatedAt": "2025-11-04T14:29:45.755Z",
                "emailVerified": false,
                "image": null,
                "lang": [
                    "en"
                ]
            },
            {
                "email": "testuser17619244764337211@example.com",
                "image": null,
                "lang": [
                    "en"
                ],
                "templateId": [
                    28
                ],
                "twoFactorEnabled": null,
                "banReason": null,
                "canEdit": false,
                "emailVerified": false,
                "name": "Test User 1761924476433_9",
                "updatedAt": "2025-10-31T15:28:00.729Z",
                "createdAt": "2025-10-31T15:28:00.729Z",
                "id": "0uNhZqgPndxWqmb7R4KdLMLE0G1AtV77",
                "role": "demo",
                "banExpires": null,
                "banned": false
            },
            {
                "role": "scribe",
                "banReason": null,
                "updatedAt": "2025-10-31T16:49:26.554Z",
                "createdAt": "2025-10-31T16:49:26.554Z",
                "name": "Test User 1761929362179_242",
                "banExpires": null,
                "canEdit": false,
                "id": "0v1FXL56HU3OxBb957NJq9S5tTnMydr4",
                "image": null,
                "templateId": [
                    28
                ],
                "twoFactorEnabled": null,
                "banned": false,
                "email": "testuser17619293621798741@example.com",
                "emailVerified": false,
                "lang": [
                    "en"
                ]
            },
            {
                "image": null,
                "lang": [
                    "en"
                ],
                "role": "scribe",
                "createdAt": "2025-10-30T17:12:33.124Z",
                "emailVerified": false,
                "id": "0v9Pm3zf08xmYBct1fcRgNqJwWihLrIw",
                "name": "Test User 1761844348472_772",
                "banReason": null,
                "banExpires": null,
                "canEdit": false,
                "templateId": [
                    28
                ],
                "twoFactorEnabled": null,
                "updatedAt": "2025-10-30T17:12:33.124Z",
                "banned": false,
                "email": "testuser17618443484727339@example.com"
            },
            {
                "role": "scribeAdmin",
                "twoFactorEnabled": null,
                "banned": null,
                "emailVerified": false,
                "id": "0vA1TtvLiYxKinmegG3AdEXKdWgAaQGN",
                "lang": [
                    "en"
                ],
                "updatedAt": "2025-11-04T13:42:35.509Z",
                "canEdit": false,
                "image": null,
                "templateId": [
                    28
                ],
                "banExpires": null,
                "banReason": null,
                "createdAt": "2025-11-04T13:42:35.509Z",
                "email": "testuser17622637554801387@example.com",
                "name": "Test User 1762263755480_596"
            },
            {
                "image": null,
                "templateId": [
                    28
                ],
                "twoFactorEnabled": null,
                "updatedAt": "2025-11-04T14:55:37.315Z",
                "banReason": null,
                "canEdit": false,
                "email": "testuser17622681315649924@example.com",
                "id": "0VIeGdrs6BQ7CqPxiVgbknDuokZkcPQO",
                "banned": null,
                "lang": [
                    "en"
                ],
                "role": "provider",
                "createdAt": "2025-11-04T14:55:37.315Z",
                "name": "Test User 1762268131563_949",
                "banExpires": null,
                "emailVerified": false
            },
            {
                "lang": [
                    "en"
                ],
                "createdAt": "2025-11-03T16:38:50.336Z",
                "email": "testuser17621879302964854@example.com",
                "id": "0WfCSYvUK71Pc5iGVs7cMk8lndxhoanX",
                "name": "Test User 1762187930296_360",
                "banExpires": null,
                "canEdit": false,
                "image": null,
                "twoFactorEnabled": null,
                "banned": null,
                "role": "demo",
                "templateId": [
                    28
                ],
                "updatedAt": "2025-11-03T16:38:50.336Z",
                "banReason": null,
                "emailVerified": false
            },
            {
                "canEdit": false,
                "twoFactorEnabled": null,
                "updatedAt": "2025-11-03T17:09:51.356Z",
                "banned": null,
                "createdAt": "2025-11-03T17:09:51.356Z",
                "templateId": [
                    28
                ],
                "banExpires": null,
                "banReason": null,
                "email": "testuser17621897866728738@example.com",
                "emailVerified": false,
                "image": null,
                "role": "scribeAdmin",
                "id": "0WHaOJqdH9faW237safitBMWSLh5RgKu",
                "lang": [
                    "en"
                ],
                "name": "Test User 1762189786672_151"
            },
            {
                "banExpires": null,
                "banned": null,
                "email": "testuser17623599486964491@example.com",
                "templateId": [
                    28
                ],
                "updatedAt": "2025-11-05T16:25:48.724Z",
                "banReason": null,
                "createdAt": "2025-11-05T16:25:48.724Z",
                "canEdit": false,
                "emailVerified": false,
                "image": null,
                "id": "0xbrJtAMBd7cWmtoSbr00uFODYyl8e6W",
                "lang": [
                    "en"
                ],
                "name": "Test User 1762359948696_279",
                "role": "admin",
                "twoFactorEnabled": null
            },
            {
                "role": "admin",
                "email": "testuser17623651796812755@example.com",
                "name": "Test User 1762365179681_16",
                "templateId": [
                    28
                ],
                "twoFactorEnabled": null,
                "banReason": null,
                "banned": null,
                "createdAt": "2025-11-05T17:52:59.707Z",
                "image": null,
                "canEdit": false,
                "updatedAt": "2025-11-05T17:52:59.707Z",
                "banExpires": null,
                "emailVerified": false,
                "id": "0yUD9uZ060LX5AmhBgWWDqu5TvnMIAOQ",
                "lang": [
                    "en"
                ]
            },
            {
                "banned": null,
                "canEdit": false,
                "banReason": null,
                "id": "0yXBatq0M64vu8qfHnO6baFBmI5yh3Pe",
                "image": null,
                "lang": [
                    "en"
                ],
                "banExpires": null,
                "createdAt": "2025-11-02T01:57:09.945Z",
                "emailVerified": false,
                "name": "Test User 1762048629931_78",
                "templateId": [
                    28
                ],
                "email": "testuser17620486299319609@example.com",
                "role": "provider",
                "twoFactorEnabled": null,
                "updatedAt": "2025-11-02T01:57:09.945Z"
            },
            {
                "banReason": null,
                "banned": false,
                "emailVerified": false,
                "lang": [
                    "en"
                ],
                "email": "testuser17619252544257754@example.com",
                "templateId": [
                    28
                ],
                "role": "provider",
                "twoFactorEnabled": null,
                "banExpires": null,
                "canEdit": false,
                "id": "0zh1RJhIQkHcaTBhcaMrEXeZtdlyU5xv",
                "image": null,
                "createdAt": "2025-10-31T15:40:58.734Z",
                "name": "Test User 1761925254425_193",
                "updatedAt": "2025-10-31T15:40:58.734Z"
            },
            {
                "banReason": null,
                "image": null,
                "name": "Test User 1762359462834_0",
                "role": "admin",
                "twoFactorEnabled": null,
                "banExpires": null,
                "canEdit": false,
                "banned": null,
                "createdAt": "2025-11-05T16:17:47.884Z",
                "email": "testuser17623594628342805@example.com",
                "emailVerified": false,
                "lang": [
                    "en"
                ],
                "templateId": [
                    28
                ],
                "id": "0ZHObiaEeu2kGpgKUGpvGTcjedtB2jS9",
                "updatedAt": "2025-11-05T16:17:47.884Z"
            },
            {
                "banExpires": null,
                "banReason": null,
                "banned": false,
                "createdAt": "2025-10-31T15:24:21.540Z",
                "email": "testuser17619242572466124@example.com",
                "id": "0zQEa0pp3N9j0bElaUo7gIPvqsmOjrj5",
                "templateId": [
                    28
                ],
                "updatedAt": "2025-10-31T15:24:21.540Z",
                "twoFactorEnabled": null,
                "canEdit": false,
                "lang": [
                    "en"
                ],
                "emailVerified": false,
                "image": null,
                "name": "Test User 1761924257246_342",
                "role": "scribeAdmin"
            },
            {
                "email": "testuser17620486478606028@example.com",
                "image": null,
                "lang": [
                    "en"
                ],
                "role": "provider",
                "updatedAt": "2025-11-02T01:57:27.873Z",
                "banExpires": null,
                "banReason": null,
                "canEdit": false,
                "emailVerified": false,
                "name": "Test User 1762048647860_127",
                "templateId": [
                    28
                ],
                "twoFactorEnabled": null,
                "banned": null,
                "createdAt": "2025-11-02T01:57:27.873Z",
                "id": "11d4GoNwW5yWS8P29FyOvd0TQQtwuD0n"
            },
            {
                "banReason": null,
                "email": "testuser17619280965859394@example.com",
                "emailVerified": false,
                "templateId": [
                    28
                ],
                "id": "12i2NDWj5TQh7UjFKucmhcXQbMHDTldp",
                "role": "demo",
                "updatedAt": "2025-10-31T16:28:20.940Z",
                "twoFactorEnabled": null,
                "banExpires": null,
                "canEdit": false,
                "createdAt": "2025-10-31T16:28:20.940Z",
                "name": "Test User 1761928096585_716",
                "banned": false,
                "image": null,
                "lang": [
                    "en"
                ]
            },
            {
                "banned": null,
                "email": "testuser17623528889334491@example.com",
                "id": "13mdbLBNHxrpBNfImn5Ifgvxzc1AKqXZ",
                "lang": [
                    "en"
                ],
                "canEdit": false,
                "name": "Test User 1762352888933_51",
                "templateId": [
                    28
                ],
                "twoFactorEnabled": null,
                "banReason": null,
                "createdAt": "2025-11-05T14:28:13.866Z",
                "image": null,
                "emailVerified": false,
                "role": "admin",
                "updatedAt": "2025-11-05T14:28:13.866Z",
                "banExpires": null
            },
            {
                "twoFactorEnabled": null,
                "updatedAt": "2025-11-03T16:38:19.797Z",
                "createdAt": "2025-11-03T16:38:19.797Z",
                "email": "testuser17621878997725647@example.com",
                "emailVerified": false,
                "lang": [
                    "en"
                ],
                "banExpires": null,
                "banReason": null,
                "banned": null,
                "canEdit": false,
                "role": "provider",
                "templateId": [
                    28
                ],
                "image": null,
                "id": "14p2hwfDrVYHfmBryodgvG5DWvxD97tV",
                "name": "Test User 1762187899772_306"
            },
            {
                "twoFactorEnabled": null,
                "emailVerified": false,
                "image": null,
                "name": "Test User 1761928750260_667",
                "templateId": [
                    28
                ],
                "canEdit": false,
                "updatedAt": "2025-10-31T16:39:14.625Z",
                "banExpires": null,
                "createdAt": "2025-10-31T16:39:14.625Z",
                "email": "testuser17619287502608886@example.com",
                "role": "bug",
                "banReason": null,
                "banned": false,
                "id": "16cof5KyQrbxKQ44SZLQkQu7ACfBfvk8",
                "lang": [
                    "en"
                ]
            },
            {
                "banReason": null,
                "canEdit": false,
                "id": "16fsPYHK1ZypidCIwc1hG9Wccez5yy3Q",
                "name": "Test User",
                "updatedAt": "2025-11-08T17:41:41.207Z",
                "email": "testuser+1762623698808@gmail.com",
                "image": null,
                "role": "admin",
                "lang": [
                    "en"
                ],
                "twoFactorEnabled": null,
                "banExpires": null,
                "banned": null,
                "createdAt": "2025-11-08T17:41:41.207Z",
                "emailVerified": false,
                "templateId": [
                    28
                ]
            },
            {
                "canEdit": false,
                "createdAt": "2025-10-31T16:38:38.174Z",
                "image": null,
                "name": "Test User 1761928713808_939",
                "banExpires": null,
                "banReason": null,
                "banned": false,
                "twoFactorEnabled": null,
                "emailVerified": false,
                "id": "18LcoZkgdw22wR4dNP2H94W00cQKNYje",
                "templateId": [
                    28
                ],
                "updatedAt": "2025-10-31T16:38:38.174Z",
                "email": "testuser17619287138086055@example.com",
                "lang": [
                    "en"
                ],
                "role": "bug in role set"
            },
            {
                "canEdit": false,
                "createdAt": "2025-11-05T16:25:51.188Z",
                "id": "1A97znOYEaTDoglHqLjXsfDIZpwa09AS",
                "lang": [
                    "en"
                ],
                "role": "admin",
                "templateId": [
                    28
                ],
                "twoFactorEnabled": null,
                "banExpires": null,
                "email": "testuser1762359951160286@example.com",
                "emailVerified": false,
                "image": null,
                "name": "Test User 1762359951160_702",
                "updatedAt": "2025-11-05T16:25:51.188Z",
                "banReason": null,
                "banned": null
            },
            {
                "emailVerified": false,
                "role": "fix it",
                "updatedAt": "2025-10-27T15:51:54.156Z",
                "canEdit": false,
                "lang": [
                    "en"
                ],
                "banned": true,
                "id": "1AAB6GOkixJNXXeTmGiDJHZN95qgN6YA",
                "image": null,
                "name": "Test User 1761580307328",
                "templateId": [
                    28
                ],
                "email": "testuser1761580307328@gmail.com",
                "twoFactorEnabled": null,
                "banExpires": "2025-11-07T16:41:00.883Z",
                "banReason": "No reason",
                "createdAt": "2025-10-27T15:51:54.156Z"
            },
            {
                "banExpires": null,
                "banReason": null,
                "banned": null,
                "id": "1ATk7kSxStekbSldeOCj9wr5CJI7aqpv",
                "image": null,
                "role": "admin",
                "canEdit": false,
                "email": "testuser17621897977069554@example.com",
                "lang": [
                    "en"
                ],
                "name": "Test User 1762189797706_705",
                "emailVerified": false,
                "templateId": [
                    28
                ],
                "updatedAt": "2025-11-03T17:10:02.357Z",
                "createdAt": "2025-11-03T17:10:02.357Z",
                "twoFactorEnabled": null
            },
            {
                "emailVerified": false,
                "templateId": [
                    28
                ],
                "banReason": null,
                "banned": null,
                "name": "Test User 1762176188908_42",
                "createdAt": "2025-11-03T13:23:13.359Z",
                "lang": [
                    "en"
                ],
                "role": "scribe",
                "id": "1bhWNhba0zSNWAkkuCfCUI73NN2aTIWK",
                "image": null,
                "twoFactorEnabled": null,
                "updatedAt": "2025-11-03T13:23:13.359Z",
                "banExpires": null,
                "canEdit": false,
                "email": "testuser17621761889086559@example.com"
            },
            {
                "createdAt": "2025-11-05T15:05:42.550Z",
                "emailVerified": false,
                "id": "1bxMP4zYKdYzuGqBjw0GjGIj7LbLKasH",
                "image": null,
                "canEdit": false,
                "role": "admin",
                "banExpires": null,
                "banReason": null,
                "banned": null,
                "email": "testuser17623551425244718@example.com",
                "lang": [
                    "en"
                ],
                "templateId": [
                    28
                ],
                "twoFactorEnabled": null,
                "updatedAt": "2025-11-05T15:05:42.550Z",
                "name": "Test User 1762355142524_824"
            },
            {
                "canEdit": false,
                "id": "1CJKfSUCAYkHHeimwb6FWUDJXKKbc5kf",
                "twoFactorEnabled": null,
                "updatedAt": "2025-10-31T14:27:33.029Z",
                "banExpires": "2025-11-07T16:41:02.692Z",
                "createdAt": "2025-10-31T14:27:33.029Z",
                "email": "testuser17619208487839496@example.com",
                "role": "bug",
                "emailVerified": false,
                "image": null,
                "lang": [
                    "en"
                ],
                "name": "Test User 1761920848783_40",
                "templateId": [
                    28
                ],
                "banReason": "No reason",
                "banned": true
            },
            {
                "banExpires": null,
                "banReason": null,
                "emailVerified": false,
                "id": "1D3tVhyGszfZvhNpCZRKoJTYKnysNy18",
                "role": "admin",
                "updatedAt": "2025-11-04T13:27:12.461Z",
                "email": "testuser17622628276003885@example.com",
                "name": "Test User 1762262827600_988",
                "banned": null,
                "canEdit": false,
                "image": null,
                "templateId": [
                    28
                ],
                "twoFactorEnabled": null,
                "createdAt": "2025-11-04T13:27:12.461Z",
                "lang": [
                    "en"
                ]
            },
            {
                "banExpires": null,
                "id": "1EKGAQo3u9WhjfMTA7KH7c0Ehl4fomB9",
                "updatedAt": "2025-11-05T17:53:00.952Z",
                "createdAt": "2025-11-05T17:53:00.952Z",
                "image": null,
                "role": "admin",
                "email": "testuser17623651809265781@example.com",
                "name": "Test User 1762365180926_844",
                "templateId": [
                    28
                ],
                "twoFactorEnabled": null,
                "banReason": null,
                "banned": null,
                "canEdit": false,
                "emailVerified": false,
                "lang": [
                    "en"
                ]
            },
            {
                "canEdit": false,
                "id": "1el3Mnf5cphg54gfK1qwIheE1N5jqYT6",
                "role": "admin",
                "twoFactorEnabled": null,
                "createdAt": "2025-11-04T15:59:53.710Z",
                "image": null,
                "lang": [
                    "en"
                ],
                "updatedAt": "2025-11-04T15:59:53.710Z",
                "banned": null,
                "templateId": [
                    28
                ],
                "banExpires": null,
                "banReason": null,
                "email": "testuser17622719886752716@example.com",
                "emailVerified": false,
                "name": "Test User 1762271988675_152"
            },
            {
                "twoFactorEnabled": null,
                "banExpires": "2025-11-07T16:41:05.759Z",
                "email": "testuser17619267375925156@example.com",
                "image": null,
                "updatedAt": "2025-10-31T16:05:41.925Z",
                "lang": [
                    "en"
                ],
                "role": "bug in role set",
                "canEdit": false,
                "emailVerified": false,
                "name": "Test User 1761926737592_110",
                "templateId": [
                    28
                ],
                "banReason": "No reason",
                "banned": true,
                "createdAt": "2025-10-31T16:05:41.925Z",
                "id": "1eq7rstzeg7pqbRHBS1ANUTcLad3Zdzo"
            },
            {
                "emailVerified": false,
                "image": null,
                "lang": [
                    "en"
                ],
                "templateId": [
                    28
                ],
                "banExpires": "2025-11-07T16:41:01.256Z",
                "id": "1fDZahiSM3JloAlphpQ0G0GhEzLxzkvp",
                "name": "Test User 1761924795820_473",
                "twoFactorEnabled": null,
                "banned": true,
                "createdAt": "2025-10-31T15:33:20.239Z",
                "role": "demo",
                "banReason": "No reason",
                "canEdit": false,
                "email": "testuser17619247958201316@example.com",
                "updatedAt": "2025-10-31T15:33:20.239Z"
            },
            {
                "banned": null,
                "canEdit": false,
                "email": "testuser17624466184958525@example.com",
                "image": null,
                "templateId": [
                    28
                ],
                "updatedAt": "2025-11-06T16:30:23.320Z",
                "createdAt": "2025-11-06T16:30:23.320Z",
                "emailVerified": false,
                "lang": [
                    "en"
                ],
                "name": "Test User 1762446618495_661",
                "id": "1giaRxOtQue7nebhiKvhMBexgUXDfc1K",
                "role": "admin",
                "twoFactorEnabled": null,
                "banExpires": null,
                "banReason": null
            },
            {
                "templateId": [
                    28
                ],
                "email": "testuser17622665476861647@example.com",
                "image": null,
                "name": "Test User 1762266547686_36",
                "role": "admin",
                "banExpires": null,
                "banReason": null,
                "id": "1hVY3ffq2FHydBgAO6eDXvbvESVpvxjC",
                "lang": [
                    "en"
                ],
                "twoFactorEnabled": null,
                "banned": null,
                "updatedAt": "2025-11-04T14:29:12.621Z",
                "canEdit": false,
                "createdAt": "2025-11-04T14:29:12.621Z",
                "emailVerified": false
            },
            {
                "banned": true,
                "createdAt": "2025-10-31T15:34:12.107Z",
                "lang": [
                    "en"
                ],
                "canEdit": false,
                "email": "testuser17619248520817721@example.com",
                "id": "1I7SSR38owH9Duy1QDVwQ51IJxBDlKeT",
                "name": "Test User 1761924852081_389",
                "role": "demo",
                "updatedAt": "2025-10-31T15:34:12.107Z",
                "banExpires": "2025-11-07T16:41:03.079Z",
                "image": null,
                "banReason": "No reason",
                "emailVerified": false,
                "templateId": [
                    28
                ],
                "twoFactorEnabled": null
            },
            {
                "name": "Test User 1762364607993",
                "templateId": [
                    28
                ],
                "twoFactorEnabled": null,
                "banned": null,
                "canEdit": false,
                "id": "1icBIjhNYY6A9tB9NuTDCeDdM8r70A1l",
                "lang": [
                    "en"
                ],
                "role": "scribe",
                "banExpires": null,
                "createdAt": "2025-11-05T17:43:30.191Z",
                "image": null,
                "banReason": null,
                "email": "testuser1762364607993@gmail.com",
                "emailVerified": false,
                "updatedAt": "2025-11-05T17:43:30.191Z"
            },
            {
                "canEdit": false,
                "createdAt": "2025-11-03T16:39:01.559Z",
                "id": "1ihcaH0FTwhtJ5XWQ4Zw60UnD1ZthzqQ",
                "role": "admin",
                "twoFactorEnabled": null,
                "banExpires": null,
                "banReason": null,
                "emailVerified": false,
                "image": null,
                "lang": [
                    "en"
                ],
                "name": "Test User 1762187941532_130",
                "updatedAt": "2025-11-03T16:39:01.559Z",
                "banned": null,
                "email": "testuser1762187941532540@example.com",
                "templateId": [
                    28
                ]
            },
            {
                "banExpires": "2025-11-07T16:41:04.898Z",
                "image": null,
                "banReason": "No reason",
                "role": "scribe",
                "updatedAt": "2025-10-22T16:12:02.370Z",
                "name": "Edit Test User",
                "twoFactorEnabled": null,
                "banned": true,
                "createdAt": "2025-10-22T16:12:02.370Z",
                "email": "edituser+20251022t161154454z@gmail.com",
                "emailVerified": false,
                "id": "1iLpd8cjN308INJH6XL3ZxdOtsXiWhW7",
                "lang": [
                    "en"
                ],
                "canEdit": false,
                "templateId": [
                    28
                ]
            },
            {
                "banExpires": null,
                "banReason": null,
                "lang": [
                    "en"
                ],
                "name": "Test User 1762710806695_454",
                "twoFactorEnabled": null,
                "updatedAt": "2025-11-09T17:53:26.702Z",
                "banned": null,
                "createdAt": "2025-11-09T17:53:26.702Z",
                "emailVerified": false,
                "role": "admin",
                "templateId": [
                    28
                ],
                "canEdit": false,
                "image": null,
                "email": "testuser17627108066957902@example.com",
                "id": "1IPObbxET6MsW9PP4nq8sGi4fgmPSApe"
            },
            {
                "canEdit": false,
                "id": "1J5xmUMUx5jDp2qnOU17n5Sy7kaFgNsf",
                "banReason": null,
                "createdAt": "2025-11-11T17:14:14.186Z",
                "updatedAt": "2025-11-11T17:14:14.186Z",
                "banExpires": null,
                "email": "testuser17628812482689603@example.com",
                "emailVerified": false,
                "image": null,
                "lang": [
                    "en"
                ],
                "name": "Test User 1762881248268_760",
                "role": "admin",
                "banned": null,
                "templateId": [
                    28
                ],
                "twoFactorEnabled": null
            },
            {
                "name": "Test User 1762355132695_719",
                "templateId": [
                    28
                ],
                "banExpires": null,
                "image": null,
                "banReason": null,
                "emailVerified": false,
                "lang": [
                    "en"
                ],
                "role": "admin",
                "twoFactorEnabled": null,
                "canEdit": false,
                "createdAt": "2025-11-05T15:05:32.720Z",
                "updatedAt": "2025-11-05T15:05:32.720Z",
                "banned": null,
                "email": "testuser17623551326956682@example.com",
                "id": "1J8lRgaVcvyTqRRxFGGBvQpsu7QkiNkd"
            },
            {
                "name": "Test User 1762883602034_546",
                "twoFactorEnabled": null,
                "banExpires": null,
                "banned": null,
                "createdAt": "2025-11-11T17:53:22.055Z",
                "id": "1jCUymgCKCSuOzfRsjlgO9Mf7EeYTUSt",
                "lang": [
                    "en"
                ],
                "role": "admin",
                "canEdit": false,
                "email": "testuser17628836020349884@example.com",
                "emailVerified": false,
                "updatedAt": "2025-11-11T17:53:22.055Z",
                "image": null,
                "templateId": [
                    28
                ],
                "banReason": null
            },
            {
                "email": "testuser17622711807325048@example.com",
                "emailVerified": false,
                "updatedAt": "2025-11-04T15:46:25.752Z",
                "name": "Test User 1762271180732_612",
                "twoFactorEnabled": null,
                "role": "admin",
                "banned": null,
                "createdAt": "2025-11-04T15:46:25.752Z",
                "id": "1jgiuoRuHFBzqAvG5Uhvq0CWvSnyo04r",
                "image": null,
                "lang": [
                    "en"
                ],
                "banExpires": null,
                "banReason": null,
                "templateId": [
                    28
                ],
                "canEdit": false
            },
            {
                "id": "1JKVcvhmMcIDAR0CsxPfrChuzTl3DuZM",
                "canEdit": false,
                "email": "testuser17622665609235625@example.com",
                "emailVerified": false,
                "lang": [
                    "en"
                ],
                "templateId": [
                    28
                ],
                "updatedAt": "2025-11-04T14:29:25.858Z",
                "banReason": null,
                "banned": null,
                "name": "Test User 1762266560923_11",
                "role": "admin",
                "twoFactorEnabled": null,
                "banExpires": null,
                "createdAt": "2025-11-04T14:29:25.858Z",
                "image": null
            },
            {
                "createdAt": "2025-11-05T14:27:45.189Z",
                "email": "testuser17623528602552241@example.com",
                "emailVerified": false,
                "twoFactorEnabled": null,
                "banExpires": null,
                "id": "1JrdJfziiPMWnh4PvrMDO23a3E6Zdoj9",
                "lang": [
                    "en"
                ],
                "name": "Test User 1762352860255_909",
                "templateId": [
                    28
                ],
                "canEdit": false,
                "updatedAt": "2025-11-05T14:27:45.189Z",
                "banned": null,
                "image": null,
                "role": "admin",
                "banReason": null
            }
        ]
    }
}